{
  "dimension": "personal",
  "entries": [
    {
      "title": "Personal Coding Style",
      "file": "../../../../.ccw/personal/coding-style.md",
      "dimension": "personal",
      "category": "general",
      "keywords": [
        "style",
        "preference"
      ],
      "readMode": "optional",
      "priority": "medium",
      "scope": "global",
      "contentLength": 402
    },
    {
      "title": "Tool Preferences",
      "file": "../../../../.ccw/personal/tool-preferences.md",
      "dimension": "personal",
      "category": "general",
      "keywords": [
        "tool",
        "cli",
        "editor"
      ],
      "readMode": "optional",
      "priority": "low",
      "scope": "global",
      "contentLength": 197
    }
  ],
  "built_at": "2026-05-21T05:32:35.322Z"
}